{
  "users": [
    {
      "id": "5c065278fc13ae254d000028",
      "username": "dasSpielIstGut",
      "gender": "F",
      "level": 6,
      "following": 5,
      "followers": 2,
      "birth": "1917-03-10",
      "city": "南京市",
      "province": "江苏省",
      "introduce": "Ich höre gern Musik!",
      "list": {
        "creation": [
          {
            "id": "5c068e3ffc13ae455e0005dc"
          },
          {
            "id": "5c068e3ffc13ae455e0005dd"
          },
          {
            "id": "5c068e3ffc13ae455e0005de"
          },
          {
            "id": "5c068e3ffc13ae455e0005df"
          }
        ],
        "collection": [
          {
            "id": "5c068e3ffc13ae455e0005e0"
          },
          {
            "id": "5c068e3ffc13ae455e0005e1"
          }
        ]
      }
    },
    {
      "id": "5c065278fc13ae254d000029",
      "username": "hphelit1",
      "gender": "M",
      "level": 5,
      "following": 812,
      "followers": 4949,
      "birth": "2005-02-25",
      "city": "杭州市",
      "province": "浙江省",
      "introduction": "Maecenas rhoncus aliquam lacus. Morbi quis tortor id nulla ultrices aliquet. Maecenas leo odio, condimentum id, luctus nec, molestie sed, justo.",
      "list": {
        "creation": [
          {
            "id": "5c068e3ffc13ae455e0005e0"
          }
        ],
        "collection": [
          {
            "id": "5c068e3ffc13ae455e0005dc"
          },
          {
            "id": "5c068e3ffc13ae455e0005e4"
          }
        ]
      }
    },
    {
      "id": "5c065278fc13ae254d00002a",
      "username": "aduffil2",
      "gender": "M",
      "level": 4,
      "following": 572,
      "followers": 1434,
      "birth": "1975-08-22",
      "city": "郑州市",
      "province": "河南省",
      "introduction": "Duis bibendum. Morbi non quam nec dui luctus rutrum.",
      "list": {
        "creation": [
          {
            "id": "5c068e3ffc13ae455e0005e1"
          },
          {
            "id": "5c068e3ffc13ae455e0005e5"
          },
          {
            "id": "5c068e3ffc13ae455e0005e4"
          },
          {
            "id": "5c068e3ffc13ae455e0005e3"
          },
          {
            "id": "5c068e3ffc13ae455e0005e5"
          }
        ],
        "collection": [
          {
            "id": "5c068e3ffc13ae455e0005dc"
          },
          {
            "id": "5c068e3ffc13ae455e0005e0"
          },
          {
            "id": "5c068e3ffc13ae455e0005dd"
          },
          {
            "id": "5c068e3ffc13ae455e0005de"
          }
        ]
      }
    }
  ],
  "playlists": [
    {
      "id": "5c068e3ffc13ae455e0005dc",
      "name": "歌单Y-find",
      "createdAt": "2010-06-07T11:25:34Z",
      "cover": "/api/images/img/5c066ec5fc13ae1786000028.jpg",
      "user": {
        "id": "5c065278fc13ae254d000028"
      },
      "labels": [
        "经典",
        "治愈",
        "经典"
      ],
      "description": "Proin eu mi. Nulla ac enim. In tempor, turpis nec euismod scelerisque, quam turpis adipiscing lorem, vitae mattis nibh ligula nec sem. Duis aliquam convallis nunc. Proin at turpis a pede posuere nonummy.",
      "countComment": 10,
      "countShare": 9,
      "countCollection": 93,
      "countPlay": 4266,
      "songs": [
        {
          "id": "5c066a22fc13ae7908000007"
        },
        {
          "id": "5c066a22fc13ae790800000d"
        },
        {
          "id": "5c066a22fc13ae7908000014"
        },
        {
          "id": "5c066a22fc13ae7908000018"
        },
        {
          "id": "5c066a22fc13ae790800001d"
        }
      ]
    },
    {
      "id": "5c068e3ffc13ae455e0005dd",
      "name": "歌单Subin",
      "createdAt": "2006-12-10T15:59:49Z",
      "cover": "/api/images/img/5c066ec5fc13ae178600002a.jpg",
      "user": {
        "id": "5c065278fc13ae254d000028"
      },
      "labels": [],
      "description": "Sed ante. Vivamus tortor.",
      "countComment": 138,
      "countShare": 51,
      "countCollection": 6107,
      "countPlay": 356339,
      "songs": [
        {
          "id": "5c066a22fc13ae7908000007"
        },
        {
          "id": "5c066a22fc13ae790800000d"
        },
        {
          "id": "5c066a22fc13ae7908000014"
        },
        {
          "id": "5c066a22fc13ae7908000018"
        },
        {
          "id": "5c066a22fc13ae790800001d"
        },
        {
          "id": "5c066a22fc13ae7908000020"
        },
        {
          "id": "5c066a22fc13ae7908000000"
        }
      ]
    },
    {
      "id": "5c068e3ffc13ae455e0005de",
      "name": "歌单Sonsing",
      "createdAt": "2009-07-20T18:41:53Z",
      "cover": "/api/images/img/5c066ec5fc13ae178600002c.jpg",
      "user": {
        "id": "5c065278fc13ae254d000028"
      },
      "labels": [
        "舞曲"
      ],
      "description": "Suspendisse accumsan tortor quis turpis.",
      "countComment": 2,
      "countShare": 2,
      "countCollection": 8,
      "countPlay": 344,
      "songs": [
        {
          "id": "5c066a22fc13ae7908000007"
        }
      ]
    },
    {
      "id": "5c068e3ffc13ae455e0005df",
      "name": "我就是来看看歌单名称最长能写多少个字符欸",
      "createdAt": "2018-11-14T12:08:20Z",
      "cover": "/api/images/img/5c066ec5fc13ae178600002c.jpg",
      "user": {
        "id": "5c065278fc13ae254d000028"
      },
      "labels": [
        "思念",
        "旅行",
        "安静"
      ],
      "description": "好多人，特别是这儿一个搞精神分析的家伙，老是问我九月份上学后会不会用功，我看这话问得很蠢，我是说在还没做一件事情之前，又怎么会知道将来怎么做呢？我的回答是：不知道。我觉得我会，可是我又怎么能知道？我敢说，这话问得蠢。\n——《麦田里的守望者》\n\nA lot people, especially this one psychoanalyst guy they have here, keeps asking me if I'm going to apply myself when I go back to school next September. It's such a stupid question in my opinion. I mean how do you know what you're going to do till you do it? I swear it's a stupid question.\n(The Catcher in the Rye)",
      "countComment": 14,
      "countShare": 29,
      "countCollection": 3147,
      "countPlay": 826421,
      "songs": [
        {
          "id": "5c066a22fc13ae7908000007"
        },
        {
          "id": "5c066a22fc13ae790800000d"
        },
        {
          "id": "5c066a22fc13ae7908000018"
        },
        {
          "id": "5c066a22fc13ae790800001d"
        }
      ]
    },
    {
      "id": "5c068e3ffc13ae455e0005e0",
      "name": "歌单Subin",
      "createdAt": "2014-12-17T09:41:10Z",
      "cover": "/api/images/img/5c066ec5fc13ae178600002a.jpg",
      "user": {
        "id": "5c065278fc13ae254d000029"
      },
      "labels": [
        "翻唱",
        "小语种",
        "旅行"
      ],
      "description": "Proin at turpis a pede posuere nonummy. Integer non velit.",
      "countComment": 84,
      "countShare": 9,
      "countCollection": 790,
      "countPlay": 7779,
      "songs": [
        {
          "id": "5c066a22fc13ae7908000014"
        },
        {
          "id": "5c066a22fc13ae7908000018"
        },
        {
          "id": "5c066a22fc13ae790800001d"
        },
        {
          "id": "5c066a22fc13ae7908000020"
        },
        {
          "id": "5c066a22fc13ae7908000000"
        }
      ]
    },
    {
      "id": "5c068e3ffc13ae455e0005e1",
      "name": "歌单Lotlux",
      "createdAt": "2015-04-25T01:53:00Z",
      "cover": "/api/images/img/5c066ec5fc13ae178600002e.jpg",
      "user": {
        "id": "5c065278fc13ae254d00002a"
      },
      "labels": [
        "后摇"
      ],
      "description": "Quisque id justo sit amet sapien dignissim vestibulum. Vestibulum ante ipsum primis in faucibus orci luctus et ultrices posuere cubilia Curae; Nulla dapibus dolor vel est. Donec odio justo, sollicitudin ut, suscipit a, feugiat et, eros. Vestibulum ac est lacinia nisi venenatis tristique. Fusce congue, diam id ornare imperdiet, sapien urna pretium nisl, ut volutpat sapien arcu sed augue.",
      "countComment": 1,
      "countShare": 7,
      "countCollection": 86,
      "countPlay": 9329,
      "songs": [
        {
          "id": "5c066a22fc13ae7908000007"
        },
        {
          "id": "5c066a22fc13ae790800000d"
        },
        {
          "id": "5c066a22fc13ae7908000014"
        },
        {
          "id": "5c066a22fc13ae7908000018"
        },
        {
          "id": "5c066a22fc13ae790800001d"
        },
        {
          "id": "5c066a22fc13ae7908000020"
        },
        {
          "id": "5c066a22fc13ae7908000000"
        }
      ]
    },
    {
      "id": "5c068e3ffc13ae455e0005e2",
      "name": "歌单Biodex",
      "createdAt": "2014-03-27T07:40:14Z",
      "cover": "/api/images/img/5c066ec5fc13ae1786000028.jpg",
      "user": {
        "id": "5c065278fc13ae254d00002a"
      },
      "labels": [
        "浪漫",
        "清晨",
        "治愈"
      ],
      "description": "Aliquam sit amet diam in magna bibendum imperdiet. Nullam orci pede, venenatis non, sodales sed, tincidunt eu, felis. Fusce posuere felis sed lacus. Morbi sem mauris, laoreet ut, rhoncus aliquet, pulvinar sed, nisl.",
      "countComment": 0,
      "countShare": 0,
      "countCollection": 1,
      "countPlay": 80,
      "songs": [
        {
          "id": "5c066a22fc13ae7908000007"
        },
        {
          "id": "5c066a22fc13ae790800000d"
        },
        {
          "id": "5c066a22fc13ae7908000014"
        },
        {
          "id": "5c066a22fc13ae7908000018"
        },
        {
          "id": "5c066a22fc13ae790800001d"
        },
        {
          "id": "5c066a22fc13ae7908000020"
        },
        {
          "id": "5c066a22fc13ae7908000000"
        }
      ]
    },
    {
      "id": "5c068e3ffc13ae455e0005e3",
      "name": "歌单Flexidy",
      "createdAt": "2017-01-10T00:56:50Z",
      "cover": "/api/images/img/5c066ec5fc13ae178600002c.jpg",
      "user": {
        "id": "5c065278fc13ae254d00002a"
      },
      "labels": [
        "工作",
        "后摇"
      ],
      "description": "Nam dui. Proin leo odio, porttitor id, consequat in, consequat ut, nulla. Sed accumsan felis.",
      "countComment": 11,
      "countShare": 6,
      "countCollection": 356,
      "countPlay": 9461,
      "songs": [
        {
          "id": "5c066a22fc13ae7908000007"
        },
        {
          "id": "5c066a22fc13ae790800000d"
        },
        {
          "id": "5c066a22fc13ae7908000020"
        },
        {
          "id": "5c066a22fc13ae7908000000"
        }
      ]
    },
    {
      "id": "5c068e3ffc13ae455e0005e4",
      "name": "歌单Tampflex",
      "createdAt": "2016-11-02T17:07:03Z",
      "cover": "/api/images/img/5c066ec5fc13ae178600002c.jpg",
      "user": {
        "id": "5c065278fc13ae254d00002a"
      },
      "labels": [
        "民族",
        "榜单",
        "儿童"
      ],
      "description": "Aenean lectus. Pellentesque eget nunc. Donec quis orci eget orci vehicula condimentum. Curabitur in libero ut massa volutpat convallis.",
      "countComment": 130,
      "countShare": 17,
      "countCollection": 2108,
      "countPlay": 43305,
      "songs": [
        {
          "id": "5c066a22fc13ae7908000007"
        },
        {
          "id": "5c066a22fc13ae790800000d"
        },
        {
          "id": "5c066a22fc13ae7908000014"
        },
        {
          "id": "5c066a22fc13ae7908000018"
        },
        {
          "id": "5c066a22fc13ae7908000000"
        }
      ]
    },
    {
      "id": "5c068e3ffc13ae455e0005e5",
      "name": "歌单Viva",
      "createdAt": "2015-08-21T00:24:30Z",
      "cover": "/api/images/img/5c066ec5fc13ae178600002a.jpg",
      "user": {
        "id": "5c065278fc13ae254d00002a"
      },
      "labels": [
        "清新",
        "蓝调",
        "清晨"
      ],
      "description": "Sed ante. Vivamus tortor.",
      "countComment": 56,
      "countShare": 3,
      "countCollection": 3951,
      "countPlay": 120234,
      "songs": [
        {
          "id": "5c066a22fc13ae7908000018"
        },
        {
          "id": "5c066a22fc13ae790800001d"
        },
        {
          "id": "5c066a22fc13ae7908000020"
        },
        {
          "id": "5c066a22fc13ae7908000000"
        },
        {
          "id": "5c066a22fc13ae7908000007"
        },
        {
          "id": "5c066a22fc13ae790800000d"
        },
        {
          "id": "5c066a22fc13ae7908000014"
        }
      ]
    }
  ],
  "songs": [
    {
      "id": "5c066a22fc13ae7908000000",
      "name": "Just a Stranger",
      "artist": [
        {
          "id": "5c0768d3fc13ae12d0000000"
        }
      ],
      "album": {
        "id": "5c066ec5fc13ae1786000028"
      },
      "lyrics": "\nSelf Destruct\nThats what we do\nWhen we’re together\nMe and you\nWere so in love\nBut out of touch\nWith all the damage we could do\nWhat we had was beautiful until the moment it was through\nBut when all we’re left with is wreckage its time to face the truth\n\nI didn’t wanna be the one to say so\nYou didn’t wanna be the one to let go\nBut I know that we both know\nI know you know we couldn’t keep this\nHad to break it off for a million reasons\nTo bring it back to life was beyond our reaches\nNow you’re just a stranger, just a stranger\nI know you know we couldn’t keep this\nHad to break it off for a million reasons\nTo bring it back to life was beyond our reaches\nNow you’re just a stranger with all my secrets\nWe lit a spark but blew it out\nSomehow still burned this to the ground\nWe got hurt, couldn’t get out\nNow we carry the scars around\nKept falling in further down\nInto the fights we’d both allow\nAnd I kept on thinking if we keep on sinking then we’re gonna drown\nI didn’t wanna be the one to say so\nYou didn’t wanna be the one to let go\nBut I know that we both know\nI know you know we couldn’t keep this\nHad to break it off for a million reasons\nTo bring it back to life was beyond our reaches\nNow you’re just a stranger, just a stranger\nI know you know we couldn’t keep this\nHad to break it off for a million reasons\nTo bring it back to life was beyond our reaches\nNow you’re just a stranger with all my secrets\nAll my secrets, all my secrets, all my secrets\nMy secrets\nAll my secrets, all my secrets, all my secrets\nNow youre just a stranger with all my secrets\nI miss what we had I miss who we were\nI miss hanging on your every word\nI miss thinking second I miss acting first but I don’t miss getting hurt\nI miss who I was when you were around\nI miss the ups but not the downs\nBut I’ll hold on to every second we had without regret\nCause now you’re just a stranger with all my secrets",
      "countComment": 35358,
      "countPlay": {
        "week": 32,
        "total": 228
      }
    },
    {
      "id": "5c066a22fc13ae7908000007",
      "name": "Dancing Machine",
      "artist": [
        {
          "id": "5c0768d3fc13ae12d000000d"
        }
      ],
      "album": {
        "id": "5c066ec5fc13ae178600002a"
      },
      "lyrics": "",
      "countComment": 5196,
      "countPlay": {
        "week": 42,
        "total": 972
      }
    },
    {
      "id": "5c066a22fc13ae790800000d",
      "name": "Just Say Hello",
      "artist": [
        {
          "id": "5c0768d3fc13ae12d000000d"
        }
      ],
      "album": {
        "id": "5c066ec5fc13ae178600002a"
      },
      "lyrics": "",
      "countComment": 13293,
      "countPlay": {
        "week": 7,
        "total": 139
      }
    },
    {
      "id": "5c066a22fc13ae7908000014",
      "name": "Sing You To Sleep",
      "artist": [
        {
          "id": "5c0768d3fc13ae12d000000d"
        }
      ],
      "album": {
        "id": "5c066ec5fc13ae178600002a"
      },
      "lyrics": "",
      "countComment": 13293,
      "countPlay": {
        "week": 7,
        "total": 139
      }
    },
    {
      "id": "5c066a22fc13ae7908000018",
      "name": "Midnight Mind",
      "artist": [
        {
          "id": "5c0768d3fc13ae12d000000d"
        }
      ],
      "album": {
        "id": "5c066ec5fc13ae178600002a"
      },
      "lyrics": "",
      "countComment": 13293,
      "countPlay": {
        "week": 7,
        "total": 139
      }
    },
    {
      "id": "5c066a22fc13ae790800001d",
      "name": "Silent Movies",
      "artist": [
        {
          "id": "5c0768d3fc13ae12d0000016"
        }
      ],
      "album": {
        "id": "5c066ec5fc13ae178600002c"
      },
      "lyrics": "Verse 1:\nNow Jane\nStanding over in her nightgown\nShe’s got the phone cord twisted ring finger \nShe’s a sight to see\nSee jane \nWhy you staring out the window\nWith the red eyes tell me his name\nThat got you tangled up\n\nVerse 2:\nNow Jane\nShe’s a lover like a pipe bomb\nShe’s got the pink sunglasses high heels\nGonna walk it out\nNow Jane\nWhatchya doing in the backseat\nI always thought you were a front seat \nCadillac burning up the town with us\n\nPrechorus:\nShe said you feeling all right\nCause you look like hell\nI think I’m doing just fine \nAs far as i can tell\n\nChorus:\nWell its just so easy\nWhen everybody talks so carefully\nBut you’re my melatonin daydream\nPretend you don’t but you know\nYou know you know\nThat they all want you\nTheres nothing else you really can do\nAnd if you could you wouldn’t want to\nOh i know\n\nVerse 3:\nNow Jane\nWhere the hell did all your friends go\nThey got a job in the city and a kid\nUsed to be so close\nJane \nYou remember what you told me\nWhen we were standing in the bathroom,\nMidnight baby we were so messed up\n\n\n\nPrechorus:\nYou said well you can be mine\nI wouldn’t mind being yours\nI wouldn’t take up your time\nAnd i could sleep on the floor\n\nChorus:\nWell its just so easy\nWhen everybody talks so carefully\nBut your my melatonin daydream\nPretend you don’t but you know\nYou know you know\nThat they all want you\nTheres nothing else you really can do\nAnd if you could you wouldn’t want to\nOh i know",
      "countComment": 74545,
      "countPlay": {
        "week": 50,
        "total": 43
      }
    },
    {
      "id": "5c066a22fc13ae7908000020",
      "name": "Melatonin",
      "artist": [
        {
          "id": "5c0768d3fc13ae12d0000016"
        }
      ],
      "album": {
        "id": "5c066ec5fc13ae178600002e"
      },
      "lyrics": "Verse 1:\nNow Jane\nStanding over in her nightgown\nShe’s got the phone cord twisted ring finger \nShe’s a sight to see\nSee jane \nWhy you staring out the window\nWith the red eyes tell me his name\nThat got you tangled up\n\nVerse 2:\nNow Jane\nShe’s a lover like a pipe bomb\nShe’s got the pink sunglasses high heels\nGonna walk it out\nNow Jane\nWhatchya doing in the backseat\nI always thought you were a front seat \nCadillac burning up the town with us\n\nPrechorus:\nShe said you feeling all right\nCause you look like hell\nI think I’m doing just fine \nAs far as i can tell\n\nChorus:\nWell its just so easy\nWhen everybody talks so carefully\nBut you’re my melatonin daydream\nPretend you don’t but you know\nYou know you know\nThat they all want you\nTheres nothing else you really can do\nAnd if you could you wouldn’t want to\nOh i know\n\nVerse 3:\nNow Jane\nWhere the hell did all your friends go\nThey got a job in the city and a kid\nUsed to be so close\nJane \nYou remember what you told me\nWhen we were standing in the bathroom,\nMidnight baby we were so messed up\n\n\n\nPrechorus:\nYou said well you can be mine\nI wouldn’t mind being yours\nI wouldn’t take up your time\nAnd i could sleep on the floor\n\nChorus:\nWell its just so easy\nWhen everybody talks so carefully\nBut your my melatonin daydream\nPretend you don’t but you know\nYou know you know\nThat they all want you\nTheres nothing else you really can do\nAnd if you could you wouldn’t want to\nOh i know",
      "countComment": 93945,
      "countPlay": {
        "week": 67,
        "total": 566
      }
    }
  ],
  "albums": [
    {
      "id": "5c066ec5fc13ae1786000028",
      "artist": {
        "id": "5c0768d3fc13ae12d0000000"
      },
      "name": "Sonsing",
      "issue": "2018-08-10",
      "company": "此处编造有限公司",
      "type": "录音室版",
      "description": "DESCRIPTION\nThis track is about how close and intimate two people can be in a romantic relationship but when it's over they essentially just behave like complete strangers even though they know each others deepest parts.\n\nCREDITS\nWritten & Produced by: MCKOOL\nVocals: Arabella Landrum\nMixed & Mastered by: Rob Murray",
      "songs": [
        {
          "id": "5c066a22fc13ae7908000000"
        }
      ],
      "countComment": 130,
      "countShare": 79,
      "countCollection": 705
    },
    {
      "id": "5c066ec5fc13ae178600002a",
      "artist": {
        "id": "5c0768d3fc13ae12d000000d"
      },
      "name": "Julia EP",
      "issue": "2018-06-08",
      "company": "不知道是哪个公司",
      "type": "录音室版",
      "description": "CREDITS\nWritten and performed by Tyler Gelrud\nTracked and mastered by Miah\n\n版权：\ncc-nd, cc-by",
      "songs": [
        {
          "id": "5c066a22fc13ae7908000007"
        },
        {
          "id": "5c066a22fc13ae790800000d"
        },
        {
          "id": "5c066a22fc13ae7908000014"
        },
        {
          "id": "5c066a22fc13ae7908000018"
        }
      ],
      "countComment": 191,
      "countShare": 53,
      "countCollection": 272
    },
    {
      "id": "5c066ec5fc13ae178600002c",
      "artist": {
        "id": "5c0768d3fc13ae12d0000016"
      },
      "name": "Silent Movies",
      "issue": "2018-08-07",
      "company": "未知公司",
      "type": "录音室版",
      "description": "DESCRIPTION\nMelatonin, by Carter Vail, is an unusual blend of laid back guitar music and Americana banjos. Lyrically focused, the song brings to mind a west coast nostalgia, with images of pink sunglasses, wired telephones and Cadillacs.\n\nCREDITS\nWritten and Produced by Carter Vail.\n2018 Carter Vail. Exclusive worldwide license under Circulate Music/Dreamtime Palace.",
      "songs": [
        {
          "id": "5c066a22fc13ae790800001d"
        }
      ],
      "countComment": 27,
      "countShare": 46,
      "countCollection": 749
    },
    {
      "id": "5c066ec5fc13ae178600002e",
      "artist": {
        "id": "5c0768d3fc13ae12d0000016"
      },
      "name": "Melatonin",
      "issue": "2018-05-09",
      "company": "未知公司",
      "type": "录音室版",
      "description": "DESCRIPTION\nMelatonin, by Carter Vail, is an unusual blend of laid back guitar music and Americana banjos. Lyrically focused, the song brings to mind a west coast nostalgia, with images of pink sunglasses, wired telephones and Cadillacs.\n\nCREDITS\nCarter Vail - Vocals, Guitar, Writer, Producer, Mix Engineer, Mastering Engineer\nIsabella Englert - Vocals\nMax Schwartz - Banjo\nReed Gaines - Bass\nGarrett Fracol - Drums \nDalton Yodor - Guitar \nAndre Bernier - Hammond\nComment on text",
      "songs": [
        {
          "id": "5c066a22fc13ae7908000020"
        }
      ],
      "countComment": 143,
      "countShare": 11,
      "countCollection": 252
    }
  ],
  "shares": [
    {
      "action": "分享单曲",
      "date": "2018-12-04 12:00",
      "comment": {
        "text": "┗|｀O′|┛ 嗷~~",
        "image": "/api/image/bucky.jpg"
      },
      "content": {
        "type": "single",
        "name": "This is a song",
        "cover": "/api/image/cover5.jpg",
        "artist": "Who",
        "id": "single0001"
      }
    },
    {
      "action": "分享歌单",
      "date": "2018-12-04 12:00",
      "comment": {
        "text": "好听！",
        "image": "/api/image/bucky.jpg"
      },
      "content": {
        "type": "playlist",
        "name": "今天天气很不好！所以歌单名要长长长长",
        "cover": "/api/image/cover1.jpg",
        "artist": "Bucky",
        "id": "playlist0001"
      }
    },
    {
      "action": "分享专辑",
      "date": "2018-12-04 12:00",
      "comment": {
        "text": "好听！",
        "image": "/api/image/seb.jpg"
      },
      "content": {
        "type": "album",
        "name": "VERNUNFT, VERNUNFT.",
        "cover": "/api/image/cover2.jpg",
        "artist": "Tiemo Hauer",
        "id": "album0001"
      }
    },
    {
      "action": "转发",
      "date": "2018-12-04 12:00",
      "comment": {
        "text": "美~"
      },
      "content": {
        "id": "share0001",
        "type": "share",
        "action": "分享单曲",
        "comment": {
          "text": "这也太好看了吧",
          "image": [
            "/api/image/cover1.jpg",
            "/api/image/cover2.jpg",
            "/api/image/cover3.jpg",
            "/api/image/cover4.jpg",
            "/api/image/cover5.jpg",
            "/api/image/seb.jpg",
            "/api/image/bucky.jpg",
            "/api/image/scarlett.jpg",
            "/api/image/avatar.jpg"
          ]
        },
        "content": {
          "name": "VERNUNFT, VERNUNFT.",
          "cover": "/api/image/cover2.jpg",
          "artist": "Tiemo Hauer",
          "id": "album0001"
        }
      }
    },
    {
      "date": "2018-12-04 12:00",
      "comment": {
        "text": "斯嘉丽美die~",
        "image": "/api/image/scarlett.jpg"
      }
    }
  ],
  "comments": [
    {
      "id": "5c0670fefc13ae28c0000000",
      "user": {
        "id": "5c065278fc13ae254d000028"
      },
      "createdAt": "2017-12-09T19:26:10Z",
      "comment": "In hac habitasse platea dictumst. Maecenas ut massa quis augue luctus tincidunt.",
      "kudos": 56746,
      "replyTo": null,
      "object": {
        "type": "song",
        "id": "5c066a22fc13ae7908000000"
      }
    },
    {
      "id": "5c0670fefc13ae28c0000002",
      "user": {
        "id": "5c065278fc13ae254d000028"
      },
      "createdAt": "2012-11-14T15:01:28Z",
      "comment": "Integer ac neque. Duis bibendum. Morbi non quam nec dui luctus rutrum.",
      "kudos": 27158,
      "replyTo": "5c0670fefc13ae28c0000016",
      "object": {
        "type": "share",
        "id": "5c066a22fc13ae790800002b"
      }
    },
    {
      "id": "5c0670fefc13ae28c0000004",
      "user": {
        "id": "5c065278fc13ae254d000028"
      },
      "createdAt": "2011-02-20T09:34:14Z",
      "comment": "Nulla mollis molestie lorem. Quisque ut erat. Curabitur gravida nisi at nibh.",
      "kudos": 93992,
      "replyTo": null,
      "object": {
        "type": "album",
        "id": "5c066ec5fc13ae1786000028"
      }
    },
    {
      "id": "5c0670fefc13ae28c0000006",
      "user": {
        "id": "5c065278fc13ae254d000028"
      },
      "createdAt": "2018-10-16T19:05:27Z",
      "comment": "Duis aliquam convallis nunc.",
      "kudos": 43754,
      "replyTo": null,
      "object": {
        "type": "album",
        "id": "5c066ec5fc13ae178600002c"
      }
    },
    {
      "id": "5c0670fefc13ae28c0000008",
      "user": {
        "id": "5c065278fc13ae254d000028"
      },
      "createdAt": "2017-01-18T11:02:38Z",
      "comment": "In hac habitasse platea dictumst. Etiam faucibus cursus urna. Ut tellus.",
      "kudos": 93827,
      "replyTo": null,
      "object": {
        "type": "album",
        "id": "5c066ec5fc13ae178600002e"
      }
    },
    {
      "id": "5c0670fefc13ae28c000000a",
      "user": {
        "id": "5c065278fc13ae254d000031"
      },
      "createdAt": "2013-06-29T08:12:45Z",
      "comment": "Nunc purus.",
      "kudos": 86595,
      "replyTo": "5c0670fefc13ae28c000001a",
      "object": {
        "type": "album",
        "id": "5c068e40fc13ae455e0005f2"
      }
    },
    {
      "id": "5c0670fefc13ae28c000000c",
      "user": {
        "id": "5c065278fc13ae254d00002c"
      },
      "createdAt": "2014-05-29T00:43:31Z",
      "comment": "Pellentesque at nulla.",
      "kudos": 6365,
      "replyTo": "5c0670fefc13ae28c0000020",
      "object": {
        "type": "song",
        "id": "5c068e40fc13ae455e0005f9"
      }
    },
    {
      "id": "5c0670fefc13ae28c000000e",
      "user": {
        "id": "5c065278fc13ae254d00002b"
      },
      "createdAt": "2014-10-28T22:29:57Z",
      "comment": "Donec diam neque, vestibulum eget, vulputate ut, ultrices vel, augue. Vestibulum ante ipsum primis in faucibus orci luctus et ultrices posuere cubilia Curae; Donec pharetra, magna vestibulum aliquet ultrices, erat tortor sollicitudin mi, sit amet lobortis sapien sapien non mi.",
      "kudos": 30342,
      "replyTo": "5c0670fefc13ae28c000000e",
      "object": {
        "type": "playlist",
        "id": "5c068e40fc13ae455e0005f3"
      }
    },
    {
      "id": "5c0670fefc13ae28c0000010",
      "user": {
        "id": "5c065278fc13ae254d00002c"
      },
      "createdAt": "2014-06-30T15:02:46Z",
      "comment": "Maecenas ut massa quis augue luctus tincidunt. Nulla mollis molestie lorem.",
      "kudos": 46493,
      "replyTo": "5c0670fefc13ae28c000000c",
      "object": {
        "type": "playlist",
        "id": "5c066ec5fc13ae178600002e"
      }
    },
    {
      "id": "5c0670fefc13ae28c0000012",
      "user": {
        "id": "5c065278fc13ae254d000028"
      },
      "createdAt": "2012-03-05T22:46:34Z",
      "comment": "Proin eu mi. Nulla ac enim.",
      "kudos": 94281,
      "replyTo": null,
      "object": {
        "type": "song",
        "id": "5c066a22fc13ae7908000018"
      }
    },
    {
      "id": "5c0670fefc13ae28c0000014",
      "user": {
        "id": "5c065278fc13ae254d00002c"
      },
      "createdAt": "2012-11-04T08:59:40Z",
      "comment": "Phasellus id sapien in sapien iaculis congue. Vivamus metus arcu, adipiscing molestie, hendrerit at, vulputate vitae, nisl. Aenean lectus.",
      "kudos": 90165,
      "replyTo": null,
      "object": {
        "type": "album",
        "id": "5c066a22fc13ae7908000031"
      }
    },
    {
      "id": "5c0670fefc13ae28c0000016",
      "user": {
        "id": "5c065278fc13ae254d000029"
      },
      "createdAt": "2015-12-20T11:56:48Z",
      "comment": "Etiam justo. Etiam pretium iaculis justo.",
      "kudos": 3718,
      "replyTo": "5c0670fefc13ae28c0000002",
      "object": {
        "type": "playlist",
        "id": "5c068e3ffc13ae455e0005ec"
      }
    },
    {
      "id": "5c0670fefc13ae28c0000018",
      "user": {
        "id": "5c065278fc13ae254d00002a"
      },
      "createdAt": "2011-03-22T16:46:52Z",
      "comment": "Vestibulum ante ipsum primis in faucibus orci luctus et ultrices posuere cubilia Curae; Duis faucibus accumsan odio. Curabitur convallis. Duis consequat dui nec nisi volutpat eleifend.",
      "kudos": 11614,
      "replyTo": null,
      "object": {
        "type": "song",
        "id": "5c068e3ffc13ae455e0005e5"
      }
    },
    {
      "id": "5c0670fefc13ae28c000001a",
      "user": {
        "id": "5c065278fc13ae254d00002f"
      },
      "createdAt": "2014-11-08T14:23:35Z",
      "comment": "Nunc nisl. Duis bibendum, felis sed interdum venenatis, turpis enim blandit mi, in porttitor pede justo eu massa. Donec dapibus.",
      "kudos": 92119,
      "replyTo": null,
      "object": {
        "type": "album",
        "id": "5c066a22fc13ae7908000018"
      }
    },
    {
      "id": "5c0670fefc13ae28c000001c",
      "user": {
        "id": "5c065278fc13ae254d00002f"
      },
      "createdAt": "2012-10-11T10:16:28Z",
      "comment": "Morbi vestibulum, velit id pretium iaculis, diam erat fermentum justo, nec condimentum neque sapien placerat ante. Nulla justo. Aliquam quis turpis eget elit sodales scelerisque.",
      "kudos": 11836,
      "replyTo": "5c0670fefc13ae28c0000020",
      "object": {
        "type": "song",
        "id": "5c066ec5fc13ae1786000028"
      }
    },
    {
      "id": "5c0670fefc13ae28c000001e",
      "user": {
        "id": "5c065278fc13ae254d00002d"
      },
      "createdAt": "2013-04-20T20:00:13Z",
      "comment": "Donec ut dolor.",
      "kudos": 36104,
      "replyTo": null,
      "object": {
        "type": "album",
        "id": "5c066a22fc13ae7908000007"
      }
    },
    {
      "id": "5c0670fefc13ae28c0000020",
      "user": {
        "id": "5c065278fc13ae254d00002c"
      },
      "createdAt": "2015-12-17T18:40:04Z",
      "comment": "Cras in purus eu magna vulputate luctus. Cum sociis natoque penatibus et magnis dis parturient montes, nascetur ridiculus mus. Vivamus vestibulum sagittis sapien.",
      "kudos": 40892,
      "replyTo": null,
      "object": {
        "type": "share",
        "id": "5c068e3ffc13ae455e0005ed"
      }
    },
    {
      "id": "5c0670fefc13ae28c0000022",
      "user": {
        "id": "5c065278fc13ae254d00002d"
      },
      "createdAt": "2013-08-16T07:47:48Z",
      "comment": "Donec semper sapien a libero.",
      "kudos": 96662,
      "replyTo": "5c0670fefc13ae28c0000004",
      "object": {
        "type": "playlist",
        "id": "5c068e3ffc13ae455e0005e4"
      }
    },
    {
      "id": "5c0670fefc13ae28c0000024",
      "user": {
        "id": "5c065278fc13ae254d00002d"
      },
      "createdAt": "2014-08-10T14:34:39Z",
      "comment": "Mauris enim leo, rhoncus sed, vestibulum sit amet, cursus id, turpis. Integer aliquet, massa id lobortis convallis, tortor risus dapibus augue, vel accumsan tellus nisi eu orci.",
      "kudos": 92256,
      "replyTo": "5c0670fefc13ae28c0000024",
      "object": {
        "type": "album",
        "id": "5c066ec5fc13ae178600002e"
      }
    },
    {
      "id": "5c0670fefc13ae28c0000026",
      "user": {
        "id": "5c065278fc13ae254d00002b"
      },
      "createdAt": "2011-09-22T07:15:07Z",
      "comment": "Quisque erat eros, viverra eget, congue eget, semper rutrum, nulla. Nunc purus. Phasellus in felis.",
      "kudos": 57292,
      "replyTo": null,
      "object": {
        "type": "song",
        "id": "5c068e3ffc13ae455e0005ed"
      }
    }
  ],
  "artists": [
    {
      "id": "5c0768d3fc13ae12d0000000",
      "name": "MCKOOL",
      "description": "instagram.com/mckoolmusic\nfacebook.com/mckoolmusic\nsoundcloud.com/mckoolmusic",
      "albums": [
        {
          "id": "5c066ec5fc13ae1786000028"
        }
      ],
      "video": [
        {
          "id": 6600
        },
        {
          "id": 1767
        },
        {
          "id": 2751
        },
        {
          "id": 7261
        },
        {
          "id": 2078
        },
        {
          "id": 4753
        }
      ]
    },
    {
      "id": "5c0768d3fc13ae12d000000d",
      "name": "TYLER GELRUD",
      "description": "USA\n#pop #singersongwriter #love\n\nTyler Gelrud is a singer/songwriter from Orange County, CA. His debut solo release, Julia, is full of dreamy and endearing acoustic-pop songs, spilling stories spanning years and countries alike. Gelrud plans to donate portions of the EP's proceeds to SAVE, an anti-suicide non-profit that encourages individuals in need to seek help. This EP is dedicated to the memory of Julia, and individuals in need of help should call 1-800-273-8255. Visit SAVE.org for additional resources regarding depression and suicide prevention.",
      "albums": [
        {
          "id": "5c066ec5fc13ae178600002a"
        }
      ],
      "video": [
        {
          "id": 3889
        },
        {
          "id": 3509
        },
        {
          "id": 7645
        }
      ]
    },
    {
      "id": "5c0768d3fc13ae12d0000016",
      "name": "Carter Vail",
      "description": "USA\n#dreampop #indie\n\nCARTER VAIL BIOGRAPHY\nSongwriter and producer Carter Vail is an artist who's music is both deeply intriguing and down to earth, focused on the unusual characters and relationships he's developed, wrapped in his simple but enticing melodies and production. Carter Vail was born in a suburb of New York on January 15th, 1997 to a South African mother and Tennessean father, both of whom introduced Carter to vastly different musical influences which greatly impact his sound.",
      "albums": [
        {
          "id": "5c066ec5fc13ae178600002c"
        },
        {
          "id": "5c066ec5fc13ae178600002e"
        }
      ],
      "video": [
        {
          "id": 2922
        },
        {
          "id": 5061
        },
        {
          "id": 4445
        },
        {
          "id": 1923
        },
        {
          "id": 6592
        }
      ]
    }
  ]
}